planetoids/__init__.py
planetoids/main.py
planetoids/assets/__init__.py
planetoids/assets/fonts/PressStart2P.ttf
planetoids/assets/fonts/VT323.ttf
planetoids/assets/fonts/__init__.py
planetoids/core/__init__.py
planetoids/core/config.py
planetoids/core/game_state.py
planetoids/core/level.py
planetoids/core/life.py
planetoids/core/logger.py
planetoids/core/score.py
planetoids/core/settings.py
planetoids/core/version.txt
planetoids/core/version_checker.py
planetoids/effects/__init__.py
planetoids/effects/crt_effect.py
planetoids/entities/__init__.py
planetoids/entities/asteroid.py
planetoids/entities/bullet.py
planetoids/entities/debris.py
planetoids/entities/particle.py
planetoids/entities/planet.py
planetoids/entities/player.py
planetoids/entities/powerups.py
planetoids/entities/score_popup.py
planetoids/ui/__init__.py
planetoids/ui/game_over.py
planetoids/ui/intro_animation.py
planetoids/ui/options_menu.py
planetoids/ui/pause_menu.py
planetoids/ui/start_menu.py
planetoids_game-0.7.2.dist-info/licenses/LICENSE
tests/__init__.py
tests/test_player.py
planetoids_game-0.7.2.dist-info/METADATA
planetoids_game-0.7.2.dist-info/WHEEL
planetoids_game-0.7.2.dist-info/entry_points.txt
planetoids_game-0.7.2.dist-info/top_level.txt
planetoids_game-0.7.2.dist-info/RECORD
