Metadata-Version: 2.4
Name: planetoids-game
Version: 0.7.2
Summary: A retro-style space shooter game built with Pygame.
Home-page: https://github.com/chris-greening/planetoids
Author: Chris Greening
Author-email: chris@christophergreening.com
Classifier: Programming Language :: Python :: 3
Classifier: License :: OSI Approved :: MIT License
Classifier: Operating System :: OS Independent
Classifier: Topic :: Games/Entertainment
Requires-Python: >=3.7
License-File: LICENSE
Requires-Dist: pygame
Requires-Dist: appdirs
Dynamic: author
Dynamic: author-email
Dynamic: classifier
Dynamic: description
Dynamic: description-content-type
Dynamic: home-page
Dynamic: license-file
Dynamic: requires-dist
Dynamic: requires-python
Dynamic: summary
